<?xml version='1.0' encoding='UTF-8'?>
<nfe>
<DataEmissao>26/09/2022</DataEmissao>
<NotaFiscal>17333</NotaFiscal>
<Warehouse>WHVIX</Warehouse>
<CidadeOrigem>Vitoria</CidadeOrigem>
<CidadeDestino>Belo Horizonte</CidadeDestino>
<CodCliente>66230</CodCliente>
<TotalNotaFiscal>1121,15</TotalNotaFiscal>
<Volumes>3</Volumes>
<PesoBruto>2,005</PesoBruto>
<CodTransportadora>950015</CodTransportadora>
<Transportadora>PagLog</Transportadora>
<CentroDistribuicao>Porto Alegre</CentroDistribuicao>
<TipoTransporte>Convencional</TipoTransporte>
<PrazoContratado>5</PrazoContratado>
<DataColeta>27/09/2022</DataColeta>
<DataEntrega>04/10/2022</DataEntrega>
<Ocorrencia>Nenhuma</Ocorrencia>
</nfe>
