<?xml version='1.0' encoding='UTF-8'?>
<nfe>
<DataEmissao>07/01/2023</DataEmissao>
<NotaFiscal>17677</NotaFiscal>
<Warehouse>WHVCP</Warehouse>
<CidadeOrigem>Campinas</CidadeOrigem>
<CidadeDestino>Recife</CidadeDestino>
<CodCliente>66369</CodCliente>
<TotalNotaFiscal>1159,18</TotalNotaFiscal>
<Volumes>1</Volumes>
<PesoBruto>1,232</PesoBruto>
<CodTransportadora>940021</CodTransportadora>
<Transportadora>Sampa Fretes</Transportadora>
<CentroDistribuicao>Guarulhos</CentroDistribuicao>
<TipoTransporte>Convencional</TipoTransporte>
<PrazoContratado>5</PrazoContratado>
<DataColeta>08/01/2023</DataColeta>
<DataEntrega>12/01/2023</DataEntrega>
<Ocorrencia>Nenhuma</Ocorrencia>
</nfe>
