<?xml version='1.0' encoding='UTF-8'?>
<nfe>
<DataEmissao>30/01/2023</DataEmissao>
<NotaFiscal>17781</NotaFiscal>
<Warehouse>WHSJC</Warehouse>
<CidadeOrigem>Sao Jose dos Campos</CidadeOrigem>
<CidadeDestino>Belo Horizonte</CidadeDestino>
<CodCliente>66359</CodCliente>
<TotalNotaFiscal>17,76</TotalNotaFiscal>
<Volumes>1</Volumes>
<PesoBruto>1,19</PesoBruto>
<CodTransportadora>960019</CodTransportadora>
<Transportadora>Minaspress</Transportadora>
<CentroDistribuicao>Belo Horizonte</CentroDistribuicao>
<TipoTransporte>Convencional</TipoTransporte>
<PrazoContratado>4</PrazoContratado>
<DataColeta>31/01/2023</DataColeta>
<DataEntrega>09/02/2023</DataEntrega>
<Ocorrencia>Nenhuma</Ocorrencia>
</nfe>
