<?xml version='1.0' encoding='UTF-8'?>
<nfe>
<DataEmissao>19/04/2023</DataEmissao>
<NotaFiscal>18232</NotaFiscal>
<Warehouse>WHRIO</Warehouse>
<CidadeOrigem>Rio De Janeiro</CidadeOrigem>
<CidadeDestino>Manaus</CidadeDestino>
<CodCliente>66247</CodCliente>
<TotalNotaFiscal>4026,14</TotalNotaFiscal>
<Volumes>5</Volumes>
<PesoBruto>23,469</PesoBruto>
<CodTransportadora>960019</CodTransportadora>
<Transportadora>Minaspress</Transportadora>
<CentroDistribuicao>Belo Horizonte</CentroDistribuicao>
<TipoTransporte>Convencional</TipoTransporte>
<PrazoContratado>11</PrazoContratado>
<DataColeta>19/04/2023</DataColeta>
<DataEntrega>20/04/2023</DataEntrega>
<Ocorrencia>Nenhuma</Ocorrencia>
</nfe>
